{"Type":"Material","Name":"Default Diffuse Material","Guid":"9d392707-5aa6-4052-baa9-f0cefe652c18","RenderMode":"Opaque","Path":"D:\\VSProject\\KritiaEngine\\Assets\\New Material.mat.json","Albedo":[1.0,1.0,1.0],"Shininess":32.0,"GPUInstancingEnabled":false,"MainTexture":"{\"Type\":\"Texture\",\"Name\":\"container_diffuse\",\"Guid\":\"6f3c030b-29b3-41f9-b878-93c686f050fa\",\"Path\":\"D:\\\\VSProject\\\\KritiaEngine\\\\Assets\\\\Textures\\\\container_diffuse.png\"}","SpecularMap":"Null","NormalMap":"Null","ParallaxMap":"Null","Shader":"{\"Type\":\"Shader\",\"VertexPath\":\"D:/VSProject/KritiaEngine/StandardShader/BlinnPhongShader.vs\",\"FragmentPath\":\"D:/VSProject/KritiaEngine/StandardShader/BlinnPhongShader.fs\",\"GeometryPath\":\"Null\"}"}
